odoo/addons/ssi_psychology_intervention/README.rst
odoo/addons/ssi_psychology_intervention/__init__.py
odoo/addons/ssi_psychology_intervention/__manifest__.py
odoo/addons/ssi_psychology_intervention/data/approval_template_data.xml
odoo/addons/ssi_psychology_intervention/data/ir_sequence_data.xml
odoo/addons/ssi_psychology_intervention/data/policy_template_data.xml
odoo/addons/ssi_psychology_intervention/data/sequence_template_data.xml
odoo/addons/ssi_psychology_intervention/models/__init__.py
odoo/addons/ssi_psychology_intervention/models/psychology_intervention.py
odoo/addons/ssi_psychology_intervention/models/psychology_intervention_type.py
odoo/addons/ssi_psychology_intervention/security/ir.model.access.csv
odoo/addons/ssi_psychology_intervention/security/ir_module_category_data.xml
odoo/addons/ssi_psychology_intervention/security/ir_rule_data.xml
odoo/addons/ssi_psychology_intervention/security/res_group_data.xml
odoo/addons/ssi_psychology_intervention/static/description/icon.png
odoo/addons/ssi_psychology_intervention/views/psychology_intervention_type_views.xml
odoo/addons/ssi_psychology_intervention/views/psychology_intervention_views.xml
odoo14_addon_ssi_psychology_intervention-14.0.1.2.0.dist-info/METADATA
odoo14_addon_ssi_psychology_intervention-14.0.1.2.0.dist-info/WHEEL
odoo14_addon_ssi_psychology_intervention-14.0.1.2.0.dist-info/top_level.txt
odoo14_addon_ssi_psychology_intervention-14.0.1.2.0.dist-info/RECORD
